[
 {
  "table":"DDTYPES",
  "data":
  [
   {
    "TYPENAME":"ZCL_CUSTOM_STK_CORRECTION",
    "STATE":"A",
    "TYPEKIND":"CLAS"
   }
  ]
 },
 {
  "table":"SEOCLASS",
  "data":
  [
   {
    "CLSNAME":"ZCL_CUSTOM_STK_CORRECTION",
    "CLSTYPE":0,
    "UUID":"vZIUuKMfHt64wIJYuC3fow==",
    "REMOTE":""
   }
  ]
 },
 {
  "table":"SEOCLASSDF",
  "data":
  [
   {
    "CLSNAME":"ZCL_CUSTOM_STK_CORRECTION",
    "VERSION":1,
    "CATEGORY":0,
    "EXPOSURE":2,
    "STATE":1,
    "RELEASE":0,
    "AUTHOR":"",
    "CREATEDON":"2024-03-14",
    "CHANGEDBY":"",
    "CHANGEDON":"0000-00-00",
    "CHGDANYBY":"",
    "CHGDANYON":"0000-00-00",
    "CLSEMBED":"",
    "CLSABSTRCT":"",
    "CLSFINAL":"X",
    "CLSCCINCL":"X",
    "CLSDEFATT":"",
    "CLSDEFMTD":"",
    "REFCLSNAME":"",
    "FIXPT":"X",
    "VARCL":"",
    "UNICODE":"5",
    "RSTAT":"",
    "CLSBCIMPL":"",
    "R3RELEASE":"795",
    "CLSBCTRANS":"",
    "CLSBCCAT":0,
    "CLSBCNODEL":"",
    "CLSADDON":"",
    "MSG_ID":"",
    "CLSPROXY":"",
    "CLSSHAREDMEMORY":"",
    "WITH_UNIT_TESTS":"X",
    "DURATION_TYPE":"0",
    "RISK_LEVEL":"0",
    "WITHIN_PACKAGE":""
   }
  ]
 },
 {
  "table":"SEOCLASSTX",
  "data":
  [
   {
    "CLSNAME":"ZCL_CUSTOM_STK_CORRECTION",
    "LANGU":"E",
    "DESCRIPT":"Stok Düzeltme Programı"
   }
  ]
 },
 {
  "table":"SEOCOMPO",
  "data":
  [
   {
    "CLSNAME":"ZCL_CUSTOM_STK_CORRECTION",
    "CMPNAME":"GET_DATA",
    "CMPTYPE":1,
    "MTDTYPE":0,
    "MTDTYPE2":0
   },
   {
    "CLSNAME":"ZCL_CUSTOM_STK_CORRECTION",
    "CMPNAME":"GET_FILTER_PARAMETER",
    "CMPTYPE":1,
    "MTDTYPE":0,
    "MTDTYPE2":0
   },
   {
    "CLSNAME":"ZCL_CUSTOM_STK_CORRECTION",
    "CMPNAME":"GV_DATE1",
    "CMPTYPE":0,
    "MTDTYPE":0,
    "MTDTYPE2":0
   },
   {
    "CLSNAME":"ZCL_CUSTOM_STK_CORRECTION",
    "CMPNAME":"MO_REGULATIVE_COMMON",
    "CMPTYPE":0,
    "MTDTYPE":0,
    "MTDTYPE2":0
   },
   {
    "CLSNAME":"ZCL_CUSTOM_STK_CORRECTION",
    "CMPNAME":"MR_STOCK_HKONT",
    "CMPTYPE":0,
    "MTDTYPE":0,
    "MTDTYPE2":0
   },
   {
    "CLSNAME":"ZCL_CUSTOM_STK_CORRECTION",
    "CMPNAME":"MS_BANK_BORT",
    "CMPTYPE":0,
    "MTDTYPE":0,
    "MTDTYPE2":0
   },
   {
    "CLSNAME":"ZCL_CUSTOM_STK_CORRECTION",
    "CMPNAME":"MS_BANK_REPORT",
    "CMPTYPE":0,
    "MTDTYPE":0,
    "MTDTYPE2":0
   },
   {
    "CLSNAME":"ZCL_CUSTOM_STK_CORRECTION",
    "CMPNAME":"MS_BANK_TRANS",
    "CMPTYPE":0,
    "MTDTYPE":0,
    "MTDTYPE2":0
   },
   {
    "CLSNAME":"ZCL_CUSTOM_STK_CORRECTION",
    "CMPNAME":"MS_HKONT",
    "CMPTYPE":0,
    "MTDTYPE":0,
    "MTDTYPE2":0
   },
   {
    "CLSNAME":"ZCL_CUSTOM_STK_CORRECTION",
    "CMPNAME":"MS_LOG",
    "CMPTYPE":0,
    "MTDTYPE":0,
    "MTDTYPE2":0
   },
   {
    "CLSNAME":"ZCL_CUSTOM_STK_CORRECTION",
    "CMPNAME":"MT_ACCOUNT_BALANCES",
    "CMPTYPE":0,
    "MTDTYPE":0,
    "MTDTYPE2":0
   },
   {
    "CLSNAME":"ZCL_CUSTOM_STK_CORRECTION",
    "CMPNAME":"MT_ACC_VAL",
    "CMPTYPE":0,
    "MTDTYPE":0,
    "MTDTYPE2":0
   },
   {
    "CLSNAME":"ZCL_CUSTOM_STK_CORRECTION",
    "CMPNAME":"MT_CORR_LOG",
    "CMPTYPE":0,
    "MTDTYPE":0,
    "MTDTYPE2":0
   },
   {
    "CLSNAME":"ZCL_CUSTOM_STK_CORRECTION",
    "CMPNAME":"MT_HKONT",
    "CMPTYPE":0,
    "MTDTYPE":0,
    "MTDTYPE2":0
   },
   {
    "CLSNAME":"ZCL_CUSTOM_STK_CORRECTION",
    "CMPNAME":"MT_LOG",
    "CMPTYPE":0,
    "MTDTYPE":0,
    "MTDTYPE2":0
   },
   {
    "CLSNAME":"ZCL_CUSTOM_STK_CORRECTION",
    "CMPNAME":"MT_SKAT",
    "CMPTYPE":0,
    "MTDTYPE":0,
    "MTDTYPE2":0
   },
   {
    "CLSNAME":"ZCL_CUSTOM_STK_CORRECTION",
    "CMPNAME":"MT_STOCK",
    "CMPTYPE":0,
    "MTDTYPE":0,
    "MTDTYPE2":0
   },
   {
    "CLSNAME":"ZCL_CUSTOM_STK_CORRECTION",
    "CMPNAME":"MT_STSPE",
    "CMPTYPE":0,
    "MTDTYPE":0,
    "MTDTYPE2":0
   },
   {
    "CLSNAME":"ZCL_CUSTOM_STK_CORRECTION",
    "CMPNAME":"MT_T001",
    "CMPTYPE":0,
    "MTDTYPE":0,
    "MTDTYPE2":0
   },
   {
    "CLSNAME":"ZCL_CUSTOM_STK_CORRECTION",
    "CMPNAME":"MV_AVARAGE_METHOD",
    "CMPTYPE":0,
    "MTDTYPE":0,
    "MTDTYPE2":0
   },
   {
    "CLSNAME":"ZCL_CUSTOM_STK_CORRECTION",
    "CMPNAME":"MV_COMPANY_CODE",
    "CMPTYPE":0,
    "MTDTYPE":0,
    "MTDTYPE2":0
   },
   {
    "CLSNAME":"ZCL_CUSTOM_STK_CORRECTION",
    "CMPNAME":"MV_PERIOD",
    "CMPTYPE":0,
    "MTDTYPE":0,
    "MTDTYPE2":0
   },
   {
    "CLSNAME":"ZCL_CUSTOM_STK_CORRECTION",
    "CMPNAME":"MV_RLDNR",
    "CMPTYPE":0,
    "MTDTYPE":0,
    "MTDTYPE2":0
   },
   {
    "CLSNAME":"ZCL_CUSTOM_STK_CORRECTION",
    "CMPNAME":"MV_RTYPE",
    "CMPTYPE":0,
    "MTDTYPE":0,
    "MTDTYPE2":0
   },
   {
    "CLSNAME":"ZCL_CUSTOM_STK_CORRECTION",
    "CMPNAME":"MV_STOCK_HKONT",
    "CMPTYPE":0,
    "MTDTYPE":0,
    "MTDTYPE2":0
   },
   {
    "CLSNAME":"ZCL_CUSTOM_STK_CORRECTION",
    "CMPNAME":"PROCESS_DATA",
    "CMPTYPE":1,
    "MTDTYPE":0,
    "MTDTYPE2":0
   },
   {
    "CLSNAME":"ZCL_CUSTOM_STK_CORRECTION",
    "CMPNAME":"SET_DATA",
    "CMPTYPE":1,
    "MTDTYPE":0,
    "MTDTYPE2":0
   }
  ]
 },
 {
  "table":"SEOCOMPODF",
  "data":
  [
   {
    "CLSNAME":"ZCL_CUSTOM_STK_CORRECTION",
    "CMPNAME":"GET_DATA",
    "VERSION":1,
    "ALIAS":"",
    "REDEFIN":"",
    "EXPOSURE":2,
    "STATE":1,
    "EDITORDER":2,
    "LOCKED":"",
    "DISPID":0,
    "R3RELEASE":"",
    "AUTHOR":"",
    "CREATEDON":"2024-03-15",
    "CHANGEDBY":"",
    "CHANGEDON":"0000-00-00",
    "MTDDECLTYP":0,
    "MTDABSTRCT":"",
    "MTDFINAL":"",
    "DSRNOTEOM":"",
    "EDTX":"",
    "MTDNEWEXC":"",
    "MTDREPLACE":"",
    "MTDOPTNL":"",
    "MTDAMDPRDONLY":"",
    "MTDAMDPCDSCLNT":"",
    "MTDAMDPCLNTINDEP":"",
    "ATTDECLTYP":0,
    "ATTDYNAMIC":"",
    "ATTGETMTD":"",
    "ATTSETMTD":"",
    "ATTRDONLY":"",
    "ATTVALUE":"",
    "ATTPERSIST":"",
    "ATTBUSOBJ":"",
    "ATTKEYFLD":"",
    "ATTEXPVIRT":0,
    "EVTDECLTYP":0,
    "TYPDUMMY":"",
    "TYPTYPE":0,
    "TYPE":"",
    "TABLEOF":"",
    "SRCROW1":0,
    "SRCCOLUMN1":0,
    "SRCROW2":0,
    "SRCCOLUMN2":0,
    "REFCLSNAME":"",
    "REFINTNAME":"",
    "REFCMPNAME":"",
    "BCMTDINST":"",
    "BCMTDCAT":0,
    "BCMTDDIA":"",
    "BCMTDCOM":"",
    "BCMTDSYN":0,
    "BCEVTCAT":0,
    "TYPESRC_LENG":0,
    "TYPESRC":""
   },
   {
    "CLSNAME":"ZCL_CUSTOM_STK_CORRECTION",
    "CMPNAME":"GET_FILTER_PARAMETER",
    "VERSION":1,
    "ALIAS":"",
    "REDEFIN":"",
    "EXPOSURE":2,
    "STATE":1,
    "EDITORDER":1,
    "LOCKED":"",
    "DISPID":0,
    "R3RELEASE":"",
    "AUTHOR":"",
    "CREATEDON":"2024-03-15",
    "CHANGEDBY":"",
    "CHANGEDON":"0000-00-00",
    "MTDDECLTYP":0,
    "MTDABSTRCT":"",
    "MTDFINAL":"",
    "DSRNOTEOM":"",
    "EDTX":"",
    "MTDNEWEXC":"",
    "MTDREPLACE":"",
    "MTDOPTNL":"",
    "MTDAMDPRDONLY":"",
    "MTDAMDPCDSCLNT":"",
    "MTDAMDPCLNTINDEP":"",
    "ATTDECLTYP":0,
    "ATTDYNAMIC":"",
    "ATTGETMTD":"",
    "ATTSETMTD":"",
    "ATTRDONLY":"",
    "ATTVALUE":"",
    "ATTPERSIST":"",
    "ATTBUSOBJ":"",
    "ATTKEYFLD":"",
    "ATTEXPVIRT":0,
    "EVTDECLTYP":0,
    "TYPDUMMY":"",
    "TYPTYPE":0,
    "TYPE":"",
    "TABLEOF":"",
    "SRCROW1":0,
    "SRCCOLUMN1":0,
    "SRCROW2":0,
    "SRCCOLUMN2":0,
    "REFCLSNAME":"",
    "REFINTNAME":"",
    "REFCMPNAME":"",
    "BCMTDINST":"",
    "BCMTDCAT":0,
    "BCMTDDIA":"",
    "BCMTDCOM":"",
    "BCMTDSYN":0,
    "BCEVTCAT":0,
    "TYPESRC_LENG":0,
    "TYPESRC":""
   },
   {
    "CLSNAME":"ZCL_CUSTOM_STK_CORRECTION",
    "CMPNAME":"GV_DATE1",
    "VERSION":1,
    "ALIAS":"",
    "REDEFIN":"",
    "EXPOSURE":2,
    "STATE":1,
    "EDITORDER":17,
    "LOCKED":"",
    "DISPID":0,
    "R3RELEASE":"",
    "AUTHOR":"",
    "CREATEDON":"2024-03-15",
    "CHANGEDBY":"",
    "CHANGEDON":"0000-00-00",
    "MTDDECLTYP":0,
    "MTDABSTRCT":"",
    "MTDFINAL":"",
    "DSRNOTEOM":"",
    "EDTX":"",
    "MTDNEWEXC":"",
    "MTDREPLACE":"",
    "MTDOPTNL":"",
    "MTDAMDPRDONLY":"",
    "MTDAMDPCDSCLNT":"",
    "MTDAMDPCLNTINDEP":"",
    "ATTDECLTYP":0,
    "ATTDYNAMIC":"",
    "ATTGETMTD":"",
    "ATTSETMTD":"",
    "ATTRDONLY":"",
    "ATTVALUE":"",
    "ATTPERSIST":"",
    "ATTBUSOBJ":"",
    "ATTKEYFLD":"",
    "ATTEXPVIRT":0,
    "EVTDECLTYP":0,
    "TYPDUMMY":"",
    "TYPTYPE":1,
    "TYPE":"DATUM",
    "TABLEOF":"",
    "SRCROW1":0,
    "SRCCOLUMN1":0,
    "SRCROW2":0,
    "SRCCOLUMN2":0,
    "REFCLSNAME":"",
    "REFINTNAME":"",
    "REFCMPNAME":"",
    "BCMTDINST":"",
    "BCMTDCAT":0,
    "BCMTDDIA":"",
    "BCMTDCOM":"",
    "BCMTDSYN":0,
    "BCEVTCAT":0,
    "TYPESRC_LENG":0,
    "TYPESRC":""
   },
   {
    "CLSNAME":"ZCL_CUSTOM_STK_CORRECTION",
    "CMPNAME":"MO_REGULATIVE_COMMON",
    "VERSION":1,
    "ALIAS":"",
    "REDEFIN":"",
    "EXPOSURE":2,
    "STATE":1,
    "EDITORDER":23,
    "LOCKED":"",
    "DISPID":0,
    "R3RELEASE":"",
    "AUTHOR":"",
    "CREATEDON":"2024-03-15",
    "CHANGEDBY":"",
    "CHANGEDON":"0000-00-00",
    "MTDDECLTYP":0,
    "MTDABSTRCT":"",
    "MTDFINAL":"",
    "DSRNOTEOM":"",
    "EDTX":"",
    "MTDNEWEXC":"",
    "MTDREPLACE":"",
    "MTDOPTNL":"",
    "MTDAMDPRDONLY":"",
    "MTDAMDPCDSCLNT":"",
    "MTDAMDPCLNTINDEP":"",
    "ATTDECLTYP":0,
    "ATTDYNAMIC":"",
    "ATTGETMTD":"",
    "ATTSETMTD":"",
    "ATTRDONLY":"",
    "ATTVALUE":"",
    "ATTPERSIST":"",
    "ATTBUSOBJ":"",
    "ATTKEYFLD":"",
    "ATTEXPVIRT":0,
    "EVTDECLTYP":0,
    "TYPDUMMY":"",
    "TYPTYPE":3,
    "TYPE":"ZINF_REGULATIVE_COMMON",
    "TABLEOF":"",
    "SRCROW1":0,
    "SRCCOLUMN1":0,
    "SRCROW2":0,
    "SRCCOLUMN2":0,
    "REFCLSNAME":"",
    "REFINTNAME":"",
    "REFCMPNAME":"",
    "BCMTDINST":"",
    "BCMTDCAT":0,
    "BCMTDDIA":"",
    "BCMTDCOM":"",
    "BCMTDSYN":0,
    "BCEVTCAT":0,
    "TYPESRC_LENG":0,
    "TYPESRC":""
   },
   {
    "CLSNAME":"ZCL_CUSTOM_STK_CORRECTION",
    "CMPNAME":"MR_STOCK_HKONT",
    "VERSION":1,
    "ALIAS":"",
    "REDEFIN":"",
    "EXPOSURE":2,
    "STATE":1,
    "EDITORDER":8,
    "LOCKED":"",
    "DISPID":0,
    "R3RELEASE":"",
    "AUTHOR":"",
    "CREATEDON":"2024-03-15",
    "CHANGEDBY":"",
    "CHANGEDON":"0000-00-00",
    "MTDDECLTYP":0,
    "MTDABSTRCT":"",
    "MTDFINAL":"",
    "DSRNOTEOM":"",
    "EDTX":"",
    "MTDNEWEXC":"",
    "MTDREPLACE":"",
    "MTDOPTNL":"",
    "MTDAMDPRDONLY":"",
    "MTDAMDPCDSCLNT":"",
    "MTDAMDPCLNTINDEP":"",
    "ATTDECLTYP":0,
    "ATTDYNAMIC":"",
    "ATTGETMTD":"",
    "ATTSETMTD":"",
    "ATTRDONLY":"",
    "ATTVALUE":"",
    "ATTPERSIST":"",
    "ATTBUSOBJ":"",
    "ATTKEYFLD":"",
    "ATTEXPVIRT":0,
    "EVTDECLTYP":0,
    "TYPDUMMY":"",
    "TYPTYPE":4,
    "TYPE":"",
    "TABLEOF":"",
    "SRCROW1":18,
    "SRCCOLUMN1":11,
    "SRCROW2":18,
    "SRCCOLUMN2":56,
    "REFCLSNAME":"",
    "REFINTNAME":"",
    "REFCMPNAME":"",
    "BCMTDINST":"",
    "BCMTDCAT":0,
    "BCMTDDIA":"",
    "BCMTDCOM":"",
    "BCMTDSYN":0,
    "BCEVTCAT":0,
    "TYPESRC_LENG":48,
    "TYPESRC":"mr_stock_hkont      TYPE RANGE OF zinf_e_saknr\r\n"
   },
   {
    "CLSNAME":"ZCL_CUSTOM_STK_CORRECTION",
    "CMPNAME":"MS_BANK_BORT",
    "VERSION":1,
    "ALIAS":"",
    "REDEFIN":"",
    "EXPOSURE":2,
    "STATE":1,
    "EDITORDER":11,
    "LOCKED":"",
    "DISPID":0,
    "R3RELEASE":"",
    "AUTHOR":"",
    "CREATEDON":"2024-03-15",
    "CHANGEDBY":"",
    "CHANGEDON":"0000-00-00",
    "MTDDECLTYP":0,
    "MTDABSTRCT":"",
    "MTDFINAL":"",
    "DSRNOTEOM":"",
    "EDTX":"",
    "MTDNEWEXC":"",
    "MTDREPLACE":"",
    "MTDOPTNL":"",
    "MTDAMDPRDONLY":"",
    "MTDAMDPCDSCLNT":"",
    "MTDAMDPCLNTINDEP":"",
    "ATTDECLTYP":0,
    "ATTDYNAMIC":"",
    "ATTGETMTD":"",
    "ATTSETMTD":"",
    "ATTRDONLY":"",
    "ATTVALUE":"",
    "ATTPERSIST":"",
    "ATTBUSOBJ":"",
    "ATTKEYFLD":"",
    "ATTEXPVIRT":0,
    "EVTDECLTYP":0,
    "TYPDUMMY":"",
    "TYPTYPE":1,
    "TYPE":"ZINF_T001",
    "TABLEOF":"",
    "SRCROW1":0,
    "SRCCOLUMN1":0,
    "SRCROW2":0,
    "SRCCOLUMN2":0,
    "REFCLSNAME":"",
    "REFINTNAME":"",
    "REFCMPNAME":"",
    "BCMTDINST":"",
    "BCMTDCAT":0,
    "BCMTDDIA":"",
    "BCMTDCOM":"",
    "BCMTDSYN":0,
    "BCEVTCAT":0,
    "TYPESRC_LENG":0,
    "TYPESRC":""
   },
   {
    "CLSNAME":"ZCL_CUSTOM_STK_CORRECTION",
    "CMPNAME":"MS_BANK_REPORT",
    "VERSION":1,
    "ALIAS":"",
    "REDEFIN":"",
    "EXPOSURE":2,
    "STATE":1,
    "EDITORDER":9,
    "LOCKED":"",
    "DISPID":0,
    "R3RELEASE":"",
    "AUTHOR":"",
    "CREATEDON":"2024-03-15",
    "CHANGEDBY":"",
    "CHANGEDON":"0000-00-00",
    "MTDDECLTYP":0,
    "MTDABSTRCT":"",
    "MTDFINAL":"",
    "DSRNOTEOM":"",
    "EDTX":"",
    "MTDNEWEXC":"",
    "MTDREPLACE":"",
    "MTDOPTNL":"",
    "MTDAMDPRDONLY":"",
    "MTDAMDPCDSCLNT":"",
    "MTDAMDPCLNTINDEP":"",
    "ATTDECLTYP":0,
    "ATTDYNAMIC":"",
    "ATTGETMTD":"",
    "ATTSETMTD":"",
    "ATTRDONLY":"",
    "ATTVALUE":"",
    "ATTPERSIST":"",
    "ATTBUSOBJ":"",
    "ATTKEYFLD":"",
    "ATTEXPVIRT":0,
    "EVTDECLTYP":0,
    "TYPDUMMY":"",
    "TYPTYPE":1,
    "TYPE":"ZINF_T001",
    "TABLEOF":"",
    "SRCROW1":0,
    "SRCCOLUMN1":0,
    "SRCROW2":0,
    "SRCCOLUMN2":0,
    "REFCLSNAME":"",
    "REFINTNAME":"",
    "REFCMPNAME":"",
    "BCMTDINST":"",
    "BCMTDCAT":0,
    "BCMTDDIA":"",
    "BCMTDCOM":"",
    "BCMTDSYN":0,
    "BCEVTCAT":0,
    "TYPESRC_LENG":0,
    "TYPESRC":""
   },
   {
    "CLSNAME":"ZCL_CUSTOM_STK_CORRECTION",
    "CMPNAME":"MS_BANK_TRANS",
    "VERSION":1,
    "ALIAS":"",
    "REDEFIN":"",
    "EXPOSURE":2,
    "STATE":1,
    "EDITORDER":10,
    "LOCKED":"",
    "DISPID":0,
    "R3RELEASE":"",
    "AUTHOR":"",
    "CREATEDON":"2024-03-15",
    "CHANGEDBY":"",
    "CHANGEDON":"0000-00-00",
    "MTDDECLTYP":0,
    "MTDABSTRCT":"",
    "MTDFINAL":"",
    "DSRNOTEOM":"",
    "EDTX":"",
    "MTDNEWEXC":"",
    "MTDREPLACE":"",
    "MTDOPTNL":"",
    "MTDAMDPRDONLY":"",
    "MTDAMDPCDSCLNT":"",
    "MTDAMDPCLNTINDEP":"",
    "ATTDECLTYP":0,
    "ATTDYNAMIC":"",
    "ATTGETMTD":"",
    "ATTSETMTD":"",
    "ATTRDONLY":"",
    "ATTVALUE":"",
    "ATTPERSIST":"",
    "ATTBUSOBJ":"",
    "ATTKEYFLD":"",
    "ATTEXPVIRT":0,
    "EVTDECLTYP":0,
    "TYPDUMMY":"",
    "TYPTYPE":1,
    "TYPE":"ZINF_T001",
    "TABLEOF":"",
    "SRCROW1":0,
    "SRCCOLUMN1":0,
    "SRCROW2":0,
    "SRCCOLUMN2":0,
    "REFCLSNAME":"",
    "REFINTNAME":"",
    "REFCMPNAME":"",
    "BCMTDINST":"",
    "BCMTDCAT":0,
    "BCMTDDIA":"",
    "BCMTDCOM":"",
    "BCMTDSYN":0,
    "BCEVTCAT":0,
    "TYPESRC_LENG":0,
    "TYPESRC":""
   },
   {
    "CLSNAME":"ZCL_CUSTOM_STK_CORRECTION",
    "CMPNAME":"MS_HKONT",
    "VERSION":1,
    "ALIAS":"",
    "REDEFIN":"",
    "EXPOSURE":2,
    "STATE":1,
    "EDITORDER":20,
    "LOCKED":"",
    "DISPID":0,
    "R3RELEASE":"",
    "AUTHOR":"",
    "CREATEDON":"2024-03-18",
    "CHANGEDBY":"",
    "CHANGEDON":"0000-00-00",
    "MTDDECLTYP":0,
    "MTDABSTRCT":"",
    "MTDFINAL":"",
    "DSRNOTEOM":"",
    "EDTX":"",
    "MTDNEWEXC":"",
    "MTDREPLACE":"",
    "MTDOPTNL":"",
    "MTDAMDPRDONLY":"",
    "MTDAMDPCDSCLNT":"",
    "MTDAMDPCLNTINDEP":"",
    "ATTDECLTYP":0,
    "ATTDYNAMIC":"",
    "ATTGETMTD":"",
    "ATTSETMTD":"",
    "ATTRDONLY":"",
    "ATTVALUE":"",
    "ATTPERSIST":"",
    "ATTBUSOBJ":"",
    "ATTKEYFLD":"",
    "ATTEXPVIRT":0,
    "EVTDECLTYP":0,
    "TYPDUMMY":"",
    "TYPTYPE":4,
    "TYPE":"",
    "TABLEOF":"",
    "SRCROW1":30,
    "SRCCOLUMN1":11,
    "SRCROW2":30,
    "SRCCOLUMN2":51,
    "REFCLSNAME":"",
    "REFINTNAME":"",
    "REFCMPNAME":"",
    "BCMTDINST":"",
    "BCMTDCAT":0,
    "BCMTDDIA":"",
    "BCMTDCOM":"",
    "BCMTDSYN":0,
    "BCEVTCAT":0,
    "TYPESRC_LENG":43,
    "TYPESRC":"ms_hkont            LIKE LINE OF mt_hkont\r\n"
   },
   {
    "CLSNAME":"ZCL_CUSTOM_STK_CORRECTION",
    "CMPNAME":"MS_LOG",
    "VERSION":1,
    "ALIAS":"",
    "REDEFIN":"",
    "EXPOSURE":2,
    "STATE":1,
    "EDITORDER":15,
    "LOCKED":"",
    "DISPID":0,
    "R3RELEASE":"",
    "AUTHOR":"",
    "CREATEDON":"2024-03-15",
    "CHANGEDBY":"",
    "CHANGEDON":"0000-00-00",
    "MTDDECLTYP":0,
    "MTDABSTRCT":"",
    "MTDFINAL":"",
    "DSRNOTEOM":"",
    "EDTX":"",
    "MTDNEWEXC":"",
    "MTDREPLACE":"",
    "MTDOPTNL":"",
    "MTDAMDPRDONLY":"",
    "MTDAMDPCDSCLNT":"",
    "MTDAMDPCLNTINDEP":"",
    "ATTDECLTYP":0,
    "ATTDYNAMIC":"",
    "ATTGETMTD":"",
    "ATTSETMTD":"",
    "ATTRDONLY":"",
    "ATTVALUE":"",
    "ATTPERSIST":"",
    "ATTBUSOBJ":"",
    "ATTKEYFLD":"",
    "ATTEXPVIRT":0,
    "EVTDECLTYP":0,
    "TYPDUMMY":"",
    "TYPTYPE":1,
    "TYPE":"ZINF_T002",
    "TABLEOF":"",
    "SRCROW1":0,
    "SRCCOLUMN1":0,
    "SRCROW2":0,
    "SRCCOLUMN2":0,
    "REFCLSNAME":"",
    "REFINTNAME":"",
    "REFCMPNAME":"",
    "BCMTDINST":"",
    "BCMTDCAT":0,
    "BCMTDDIA":"",
    "BCMTDCOM":"",
    "BCMTDSYN":0,
    "BCEVTCAT":0,
    "TYPESRC_LENG":0,
    "TYPESRC":""
   },
   {
    "CLSNAME":"ZCL_CUSTOM_STK_CORRECTION",
    "CMPNAME":"MT_ACCOUNT_BALANCES",
    "VERSION":1,
    "ALIAS":"",
    "REDEFIN":"",
    "EXPOSURE":2,
    "STATE":1,
    "EDITORDER":21,
    "LOCKED":"",
    "DISPID":0,
    "R3RELEASE":"",
    "AUTHOR":"",
    "CREATEDON":"2024-03-15",
    "CHANGEDBY":"",
    "CHANGEDON":"0000-00-00",
    "MTDDECLTYP":0,
    "MTDABSTRCT":"",
    "MTDFINAL":"",
    "DSRNOTEOM":"",
    "EDTX":"",
    "MTDNEWEXC":"",
    "MTDREPLACE":"",
    "MTDOPTNL":"",
    "MTDAMDPRDONLY":"",
    "MTDAMDPCDSCLNT":"",
    "MTDAMDPCLNTINDEP":"",
    "ATTDECLTYP":0,
    "ATTDYNAMIC":"",
    "ATTGETMTD":"",
    "ATTSETMTD":"",
    "ATTRDONLY":"",
    "ATTVALUE":"",
    "ATTPERSIST":"",
    "ATTBUSOBJ":"",
    "ATTKEYFLD":"",
    "ATTEXPVIRT":0,
    "EVTDECLTYP":0,
    "TYPDUMMY":"",
    "TYPTYPE":1,
    "TYPE":"ZINF_TT_BAPI1028_4",
    "TABLEOF":"",
    "SRCROW1":0,
    "SRCCOLUMN1":0,
    "SRCROW2":0,
    "SRCCOLUMN2":0,
    "REFCLSNAME":"",
    "REFINTNAME":"",
    "REFCMPNAME":"",
    "BCMTDINST":"",
    "BCMTDCAT":0,
    "BCMTDDIA":"",
    "BCMTDCOM":"",
    "BCMTDSYN":0,
    "BCEVTCAT":0,
    "TYPESRC_LENG":0,
    "TYPESRC":""
   },
   {
    "CLSNAME":"ZCL_CUSTOM_STK_CORRECTION",
    "CMPNAME":"MT_ACC_VAL",
    "VERSION":1,
    "ALIAS":"",
    "REDEFIN":"",
    "EXPOSURE":2,
    "STATE":1,
    "EDITORDER":16,
    "LOCKED":"",
    "DISPID":0,
    "R3RELEASE":"",
    "AUTHOR":"",
    "CREATEDON":"2024-03-15",
    "CHANGEDBY":"",
    "CHANGEDON":"0000-00-00",
    "MTDDECLTYP":0,
    "MTDABSTRCT":"",
    "MTDFINAL":"",
    "DSRNOTEOM":"",
    "EDTX":"",
    "MTDNEWEXC":"",
    "MTDREPLACE":"",
    "MTDOPTNL":"",
    "MTDAMDPRDONLY":"",
    "MTDAMDPCDSCLNT":"",
    "MTDAMDPCLNTINDEP":"",
    "ATTDECLTYP":0,
    "ATTDYNAMIC":"",
    "ATTGETMTD":"",
    "ATTSETMTD":"",
    "ATTRDONLY":"",
    "ATTVALUE":"",
    "ATTPERSIST":"",
    "ATTBUSOBJ":"",
    "ATTKEYFLD":"",
    "ATTEXPVIRT":0,
    "EVTDECLTYP":0,
    "TYPDUMMY":"",
    "TYPTYPE":4,
    "TYPE":"",
    "TABLEOF":"",
    "SRCROW1":26,
    "SRCCOLUMN1":11,
    "SRCROW2":26,
    "SRCCOLUMN2":73,
    "REFCLSNAME":"",
    "REFINTNAME":"",
    "REFCMPNAME":"",
    "BCMTDINST":"",
    "BCMTDCAT":0,
    "BCMTDDIA":"",
    "BCMTDCOM":"",
    "BCMTDSYN":0,
    "BCEVTCAT":0,
    "TYPESRC_LENG":65,
    "TYPESRC":"mt_acc_val          TYPE TABLE OF ddcds_customer_domain_value_t\r\n"
   },
   {
    "CLSNAME":"ZCL_CUSTOM_STK_CORRECTION",
    "CMPNAME":"MT_CORR_LOG",
    "VERSION":1,
    "ALIAS":"",
    "REDEFIN":"",
    "EXPOSURE":2,
    "STATE":1,
    "EDITORDER":13,
    "LOCKED":"",
    "DISPID":0,
    "R3RELEASE":"",
    "AUTHOR":"",
    "CREATEDON":"2024-03-15",
    "CHANGEDBY":"",
    "CHANGEDON":"0000-00-00",
    "MTDDECLTYP":0,
    "MTDABSTRCT":"",
    "MTDFINAL":"",
    "DSRNOTEOM":"",
    "EDTX":"",
    "MTDNEWEXC":"",
    "MTDREPLACE":"",
    "MTDOPTNL":"",
    "MTDAMDPRDONLY":"",
    "MTDAMDPCDSCLNT":"",
    "MTDAMDPCLNTINDEP":"",
    "ATTDECLTYP":0,
    "ATTDYNAMIC":"",
    "ATTGETMTD":"",
    "ATTSETMTD":"",
    "ATTRDONLY":"",
    "ATTVALUE":"",
    "ATTPERSIST":"",
    "ATTBUSOBJ":"",
    "ATTKEYFLD":"",
    "ATTEXPVIRT":0,
    "EVTDECLTYP":0,
    "TYPDUMMY":"",
    "TYPTYPE":4,
    "TYPE":"",
    "TABLEOF":"",
    "SRCROW1":23,
    "SRCCOLUMN1":11,
    "SRCROW2":23,
    "SRCCOLUMN2":53,
    "REFCLSNAME":"",
    "REFINTNAME":"",
    "REFCMPNAME":"",
    "BCMTDINST":"",
    "BCMTDCAT":0,
    "BCMTDDIA":"",
    "BCMTDCOM":"",
    "BCMTDSYN":0,
    "BCEVTCAT":0,
    "TYPESRC_LENG":45,
    "TYPESRC":"mt_corr_log         TYPE TABLE OF zinf_t002\r\n"
   },
   {
    "CLSNAME":"ZCL_CUSTOM_STK_CORRECTION",
    "CMPNAME":"MT_HKONT",
    "VERSION":1,
    "ALIAS":"",
    "REDEFIN":"",
    "EXPOSURE":2,
    "STATE":1,
    "EDITORDER":19,
    "LOCKED":"",
    "DISPID":0,
    "R3RELEASE":"",
    "AUTHOR":"",
    "CREATEDON":"2024-03-15",
    "CHANGEDBY":"",
    "CHANGEDON":"0000-00-00",
    "MTDDECLTYP":0,
    "MTDABSTRCT":"",
    "MTDFINAL":"",
    "DSRNOTEOM":"",
    "EDTX":"",
    "MTDNEWEXC":"",
    "MTDREPLACE":"",
    "MTDOPTNL":"",
    "MTDAMDPRDONLY":"",
    "MTDAMDPCDSCLNT":"",
    "MTDAMDPCLNTINDEP":"",
    "ATTDECLTYP":0,
    "ATTDYNAMIC":"",
    "ATTGETMTD":"",
    "ATTSETMTD":"",
    "ATTRDONLY":"",
    "ATTVALUE":"",
    "ATTPERSIST":"",
    "ATTBUSOBJ":"",
    "ATTKEYFLD":"",
    "ATTEXPVIRT":0,
    "EVTDECLTYP":0,
    "TYPDUMMY":"",
    "TYPTYPE":4,
    "TYPE":"",
    "TABLEOF":"",
    "SRCROW1":29,
    "SRCCOLUMN1":11,
    "SRCROW2":29,
    "SRCCOLUMN2":49,
    "REFCLSNAME":"",
    "REFINTNAME":"",
    "REFCMPNAME":"",
    "BCMTDINST":"",
    "BCMTDCAT":0,
    "BCMTDDIA":"",
    "BCMTDCOM":"",
    "BCMTDSYN":0,
    "BCEVTCAT":0,
    "TYPESRC_LENG":41,
    "TYPESRC":"mt_hkont            TYPE TABLE OF hkont\r\n"
   },
   {
    "CLSNAME":"ZCL_CUSTOM_STK_CORRECTION",
    "CMPNAME":"MT_LOG",
    "VERSION":1,
    "ALIAS":"",
    "REDEFIN":"",
    "EXPOSURE":2,
    "STATE":1,
    "EDITORDER":14,
    "LOCKED":"",
    "DISPID":0,
    "R3RELEASE":"",
    "AUTHOR":"",
    "CREATEDON":"2024-03-15",
    "CHANGEDBY":"",
    "CHANGEDON":"0000-00-00",
    "MTDDECLTYP":0,
    "MTDABSTRCT":"",
    "MTDFINAL":"",
    "DSRNOTEOM":"",
    "EDTX":"",
    "MTDNEWEXC":"",
    "MTDREPLACE":"",
    "MTDOPTNL":"",
    "MTDAMDPRDONLY":"",
    "MTDAMDPCDSCLNT":"",
    "MTDAMDPCLNTINDEP":"",
    "ATTDECLTYP":0,
    "ATTDYNAMIC":"",
    "ATTGETMTD":"",
    "ATTSETMTD":"",
    "ATTRDONLY":"",
    "ATTVALUE":"",
    "ATTPERSIST":"",
    "ATTBUSOBJ":"",
    "ATTKEYFLD":"",
    "ATTEXPVIRT":0,
    "EVTDECLTYP":0,
    "TYPDUMMY":"",
    "TYPTYPE":4,
    "TYPE":"",
    "TABLEOF":"",
    "SRCROW1":24,
    "SRCCOLUMN1":11,
    "SRCROW2":24,
    "SRCCOLUMN2":53,
    "REFCLSNAME":"",
    "REFINTNAME":"",
    "REFCMPNAME":"",
    "BCMTDINST":"",
    "BCMTDCAT":0,
    "BCMTDDIA":"",
    "BCMTDCOM":"",
    "BCMTDSYN":0,
    "BCEVTCAT":0,
    "TYPESRC_LENG":45,
    "TYPESRC":"mt_log              TYPE TABLE OF zinf_t002\r\n"
   },
   {
    "CLSNAME":"ZCL_CUSTOM_STK_CORRECTION",
    "CMPNAME":"MT_SKAT",
    "VERSION":1,
    "ALIAS":"",
    "REDEFIN":"",
    "EXPOSURE":2,
    "STATE":1,
    "EDITORDER":18,
    "LOCKED":"",
    "DISPID":0,
    "R3RELEASE":"",
    "AUTHOR":"",
    "CREATEDON":"2024-03-15",
    "CHANGEDBY":"",
    "CHANGEDON":"0000-00-00",
    "MTDDECLTYP":0,
    "MTDABSTRCT":"",
    "MTDFINAL":"",
    "DSRNOTEOM":"",
    "EDTX":"",
    "MTDNEWEXC":"",
    "MTDREPLACE":"",
    "MTDOPTNL":"",
    "MTDAMDPRDONLY":"",
    "MTDAMDPCDSCLNT":"",
    "MTDAMDPCLNTINDEP":"",
    "ATTDECLTYP":0,
    "ATTDYNAMIC":"",
    "ATTGETMTD":"",
    "ATTSETMTD":"",
    "ATTRDONLY":"",
    "ATTVALUE":"",
    "ATTPERSIST":"",
    "ATTBUSOBJ":"",
    "ATTKEYFLD":"",
    "ATTEXPVIRT":0,
    "EVTDECLTYP":0,
    "TYPDUMMY":"",
    "TYPTYPE":4,
    "TYPE":"",
    "TABLEOF":"",
    "SRCROW1":28,
    "SRCCOLUMN1":11,
    "SRCROW2":28,
    "SRCCOLUMN2":59,
    "REFCLSNAME":"",
    "REFINTNAME":"",
    "REFCMPNAME":"",
    "BCMTDINST":"",
    "BCMTDCAT":0,
    "BCMTDDIA":"",
    "BCMTDCOM":"",
    "BCMTDSYN":0,
    "BCEVTCAT":0,
    "TYPESRC_LENG":51,
    "TYPESRC":"mt_skat             TYPE TABLE OF I_GLAccountText\r\n"
   },
   {
    "CLSNAME":"ZCL_CUSTOM_STK_CORRECTION",
    "CMPNAME":"MT_STOCK",
    "VERSION":1,
    "ALIAS":"",
    "REDEFIN":"",
    "EXPOSURE":2,
    "STATE":1,
    "EDITORDER":7,
    "LOCKED":"",
    "DISPID":0,
    "R3RELEASE":"",
    "AUTHOR":"",
    "CREATEDON":"2024-03-15",
    "CHANGEDBY":"",
    "CHANGEDON":"0000-00-00",
    "MTDDECLTYP":0,
    "MTDABSTRCT":"",
    "MTDFINAL":"",
    "DSRNOTEOM":"",
    "EDTX":"",
    "MTDNEWEXC":"",
    "MTDREPLACE":"",
    "MTDOPTNL":"",
    "MTDAMDPRDONLY":"",
    "MTDAMDPCDSCLNT":"",
    "MTDAMDPCLNTINDEP":"",
    "ATTDECLTYP":0,
    "ATTDYNAMIC":"",
    "ATTGETMTD":"",
    "ATTSETMTD":"",
    "ATTRDONLY":"",
    "ATTVALUE":"",
    "ATTPERSIST":"",
    "ATTBUSOBJ":"",
    "ATTKEYFLD":"",
    "ATTEXPVIRT":0,
    "EVTDECLTYP":0,
    "TYPDUMMY":"",
    "TYPTYPE":4,
    "TYPE":"",
    "TABLEOF":"",
    "SRCROW1":17,
    "SRCCOLUMN1":11,
    "SRCROW2":17,
    "SRCCOLUMN2":53,
    "REFCLSNAME":"",
    "REFINTNAME":"",
    "REFCMPNAME":"",
    "BCMTDINST":"",
    "BCMTDCAT":0,
    "BCMTDDIA":"",
    "BCMTDCOM":"",
    "BCMTDSYN":0,
    "BCEVTCAT":0,
    "TYPESRC_LENG":45,
    "TYPESRC":"mt_stock            TYPE TABLE OF zinf_t007\r\n"
   },
   {
    "CLSNAME":"ZCL_CUSTOM_STK_CORRECTION",
    "CMPNAME":"MT_STSPE",
    "VERSION":1,
    "ALIAS":"",
    "REDEFIN":"",
    "EXPOSURE":2,
    "STATE":1,
    "EDITORDER":12,
    "LOCKED":"",
    "DISPID":0,
    "R3RELEASE":"",
    "AUTHOR":"",
    "CREATEDON":"2024-03-15",
    "CHANGEDBY":"",
    "CHANGEDON":"0000-00-00",
    "MTDDECLTYP":0,
    "MTDABSTRCT":"",
    "MTDFINAL":"",
    "DSRNOTEOM":"",
    "EDTX":"",
    "MTDNEWEXC":"",
    "MTDREPLACE":"",
    "MTDOPTNL":"",
    "MTDAMDPRDONLY":"",
    "MTDAMDPCDSCLNT":"",
    "MTDAMDPCLNTINDEP":"",
    "ATTDECLTYP":0,
    "ATTDYNAMIC":"",
    "ATTGETMTD":"",
    "ATTSETMTD":"",
    "ATTRDONLY":"",
    "ATTVALUE":"",
    "ATTPERSIST":"",
    "ATTBUSOBJ":"",
    "ATTKEYFLD":"",
    "ATTEXPVIRT":0,
    "EVTDECLTYP":0,
    "TYPDUMMY":"",
    "TYPTYPE":4,
    "TYPE":"",
    "TABLEOF":"",
    "SRCROW1":22,
    "SRCCOLUMN1":11,
    "SRCROW2":22,
    "SRCCOLUMN2":53,
    "REFCLSNAME":"",
    "REFINTNAME":"",
    "REFCMPNAME":"",
    "BCMTDINST":"",
    "BCMTDCAT":0,
    "BCMTDDIA":"",
    "BCMTDCOM":"",
    "BCMTDSYN":0,
    "BCEVTCAT":0,
    "TYPESRC_LENG":45,
    "TYPESRC":"mt_stspe            TYPE TABLE OF zinf_t013\r\n"
   },
   {
    "CLSNAME":"ZCL_CUSTOM_STK_CORRECTION",
    "CMPNAME":"MT_T001",
    "VERSION":1,
    "ALIAS":"",
    "REDEFIN":"",
    "EXPOSURE":2,
    "STATE":1,
    "EDITORDER":22,
    "LOCKED":"",
    "DISPID":0,
    "R3RELEASE":"",
    "AUTHOR":"",
    "CREATEDON":"2024-05-17",
    "CHANGEDBY":"",
    "CHANGEDON":"0000-00-00",
    "MTDDECLTYP":0,
    "MTDABSTRCT":"",
    "MTDFINAL":"",
    "DSRNOTEOM":"",
    "EDTX":"",
    "MTDNEWEXC":"",
    "MTDREPLACE":"",
    "MTDOPTNL":"",
    "MTDAMDPRDONLY":"",
    "MTDAMDPCDSCLNT":"",
    "MTDAMDPCLNTINDEP":"",
    "ATTDECLTYP":0,
    "ATTDYNAMIC":"",
    "ATTGETMTD":"",
    "ATTSETMTD":"",
    "ATTRDONLY":"",
    "ATTVALUE":"",
    "ATTPERSIST":"",
    "ATTBUSOBJ":"",
    "ATTKEYFLD":"",
    "ATTEXPVIRT":0,
    "EVTDECLTYP":0,
    "TYPDUMMY":"",
    "TYPTYPE":4,
    "TYPE":"",
    "TABLEOF":"",
    "SRCROW1":32,
    "SRCCOLUMN1":11,
    "SRCROW2":32,
    "SRCCOLUMN2":53,
    "REFCLSNAME":"",
    "REFINTNAME":"",
    "REFCMPNAME":"",
    "BCMTDINST":"",
    "BCMTDCAT":0,
    "BCMTDDIA":"",
    "BCMTDCOM":"",
    "BCMTDSYN":0,
    "BCEVTCAT":0,
    "TYPESRC_LENG":45,
    "TYPESRC":"mt_t001             TYPE TABLE OF zinf_t001\r\n"
   },
   {
    "CLSNAME":"ZCL_CUSTOM_STK_CORRECTION",
    "CMPNAME":"MV_AVARAGE_METHOD",
    "VERSION":1,
    "ALIAS":"",
    "REDEFIN":"",
    "EXPOSURE":2,
    "STATE":1,
    "EDITORDER":5,
    "LOCKED":"",
    "DISPID":0,
    "R3RELEASE":"",
    "AUTHOR":"",
    "CREATEDON":"2024-03-15",
    "CHANGEDBY":"",
    "CHANGEDON":"0000-00-00",
    "MTDDECLTYP":0,
    "MTDABSTRCT":"",
    "MTDFINAL":"",
    "DSRNOTEOM":"",
    "EDTX":"",
    "MTDNEWEXC":"",
    "MTDREPLACE":"",
    "MTDOPTNL":"",
    "MTDAMDPRDONLY":"",
    "MTDAMDPCDSCLNT":"",
    "MTDAMDPCLNTINDEP":"",
    "ATTDECLTYP":0,
    "ATTDYNAMIC":"",
    "ATTGETMTD":"",
    "ATTSETMTD":"",
    "ATTRDONLY":"",
    "ATTVALUE":"",
    "ATTPERSIST":"",
    "ATTBUSOBJ":"",
    "ATTKEYFLD":"",
    "ATTEXPVIRT":0,
    "EVTDECLTYP":0,
    "TYPDUMMY":"",
    "TYPTYPE":1,
    "TYPE":"ABAP_BOOLEAN",
    "TABLEOF":"",
    "SRCROW1":0,
    "SRCCOLUMN1":0,
    "SRCROW2":0,
    "SRCCOLUMN2":0,
    "REFCLSNAME":"",
    "REFINTNAME":"",
    "REFCMPNAME":"",
    "BCMTDINST":"",
    "BCMTDCAT":0,
    "BCMTDDIA":"",
    "BCMTDCOM":"",
    "BCMTDSYN":0,
    "BCEVTCAT":0,
    "TYPESRC_LENG":0,
    "TYPESRC":""
   },
   {
    "CLSNAME":"ZCL_CUSTOM_STK_CORRECTION",
    "CMPNAME":"MV_COMPANY_CODE",
    "VERSION":1,
    "ALIAS":"",
    "REDEFIN":"",
    "EXPOSURE":2,
    "STATE":1,
    "EDITORDER":1,
    "LOCKED":"",
    "DISPID":0,
    "R3RELEASE":"",
    "AUTHOR":"",
    "CREATEDON":"2024-03-15",
    "CHANGEDBY":"",
    "CHANGEDON":"0000-00-00",
    "MTDDECLTYP":0,
    "MTDABSTRCT":"",
    "MTDFINAL":"",
    "DSRNOTEOM":"",
    "EDTX":"",
    "MTDNEWEXC":"",
    "MTDREPLACE":"",
    "MTDOPTNL":"",
    "MTDAMDPRDONLY":"",
    "MTDAMDPCDSCLNT":"",
    "MTDAMDPCLNTINDEP":"",
    "ATTDECLTYP":0,
    "ATTDYNAMIC":"",
    "ATTGETMTD":"",
    "ATTSETMTD":"",
    "ATTRDONLY":"",
    "ATTVALUE":"",
    "ATTPERSIST":"",
    "ATTBUSOBJ":"",
    "ATTKEYFLD":"",
    "ATTEXPVIRT":0,
    "EVTDECLTYP":0,
    "TYPDUMMY":"",
    "TYPTYPE":1,
    "TYPE":"BUKRS",
    "TABLEOF":"",
    "SRCROW1":0,
    "SRCCOLUMN1":0,
    "SRCROW2":0,
    "SRCCOLUMN2":0,
    "REFCLSNAME":"",
    "REFINTNAME":"",
    "REFCMPNAME":"",
    "BCMTDINST":"",
    "BCMTDCAT":0,
    "BCMTDDIA":"",
    "BCMTDCOM":"",
    "BCMTDSYN":0,
    "BCEVTCAT":0,
    "TYPESRC_LENG":0,
    "TYPESRC":""
   },
   {
    "CLSNAME":"ZCL_CUSTOM_STK_CORRECTION",
    "CMPNAME":"MV_PERIOD",
    "VERSION":1,
    "ALIAS":"",
    "REDEFIN":"",
    "EXPOSURE":2,
    "STATE":1,
    "EDITORDER":2,
    "LOCKED":"",
    "DISPID":0,
    "R3RELEASE":"",
    "AUTHOR":"",
    "CREATEDON":"2024-03-15",
    "CHANGEDBY":"",
    "CHANGEDON":"0000-00-00",
    "MTDDECLTYP":0,
    "MTDABSTRCT":"",
    "MTDFINAL":"",
    "DSRNOTEOM":"",
    "EDTX":"",
    "MTDNEWEXC":"",
    "MTDREPLACE":"",
    "MTDOPTNL":"",
    "MTDAMDPRDONLY":"",
    "MTDAMDPCDSCLNT":"",
    "MTDAMDPCLNTINDEP":"",
    "ATTDECLTYP":0,
    "ATTDYNAMIC":"",
    "ATTGETMTD":"",
    "ATTSETMTD":"",
    "ATTRDONLY":"",
    "ATTVALUE":"",
    "ATTPERSIST":"",
    "ATTBUSOBJ":"",
    "ATTKEYFLD":"",
    "ATTEXPVIRT":0,
    "EVTDECLTYP":0,
    "TYPDUMMY":"",
    "TYPTYPE":1,
    "TYPE":"FINS_FYEARPERIOD",
    "TABLEOF":"",
    "SRCROW1":0,
    "SRCCOLUMN1":0,
    "SRCROW2":0,
    "SRCCOLUMN2":0,
    "REFCLSNAME":"",
    "REFINTNAME":"",
    "REFCMPNAME":"",
    "BCMTDINST":"",
    "BCMTDCAT":0,
    "BCMTDDIA":"",
    "BCMTDCOM":"",
    "BCMTDSYN":0,
    "BCEVTCAT":0,
    "TYPESRC_LENG":0,
    "TYPESRC":""
   },
   {
    "CLSNAME":"ZCL_CUSTOM_STK_CORRECTION",
    "CMPNAME":"MV_RLDNR",
    "VERSION":1,
    "ALIAS":"",
    "REDEFIN":"",
    "EXPOSURE":2,
    "STATE":1,
    "EDITORDER":3,
    "LOCKED":"",
    "DISPID":0,
    "R3RELEASE":"",
    "AUTHOR":"",
    "CREATEDON":"2024-03-15",
    "CHANGEDBY":"",
    "CHANGEDON":"0000-00-00",
    "MTDDECLTYP":0,
    "MTDABSTRCT":"",
    "MTDFINAL":"",
    "DSRNOTEOM":"",
    "EDTX":"",
    "MTDNEWEXC":"",
    "MTDREPLACE":"",
    "MTDOPTNL":"",
    "MTDAMDPRDONLY":"",
    "MTDAMDPCDSCLNT":"",
    "MTDAMDPCLNTINDEP":"",
    "ATTDECLTYP":0,
    "ATTDYNAMIC":"",
    "ATTGETMTD":"",
    "ATTSETMTD":"",
    "ATTRDONLY":"",
    "ATTVALUE":"",
    "ATTPERSIST":"",
    "ATTBUSOBJ":"",
    "ATTKEYFLD":"",
    "ATTEXPVIRT":0,
    "EVTDECLTYP":0,
    "TYPDUMMY":"",
    "TYPTYPE":1,
    "TYPE":"ZINF_E_RLDNR",
    "TABLEOF":"",
    "SRCROW1":0,
    "SRCCOLUMN1":0,
    "SRCROW2":0,
    "SRCCOLUMN2":0,
    "REFCLSNAME":"",
    "REFINTNAME":"",
    "REFCMPNAME":"",
    "BCMTDINST":"",
    "BCMTDCAT":0,
    "BCMTDDIA":"",
    "BCMTDCOM":"",
    "BCMTDSYN":0,
    "BCEVTCAT":0,
    "TYPESRC_LENG":0,
    "TYPESRC":""
   },
   {
    "CLSNAME":"ZCL_CUSTOM_STK_CORRECTION",
    "CMPNAME":"MV_RTYPE",
    "VERSION":1,
    "ALIAS":"",
    "REDEFIN":"",
    "EXPOSURE":2,
    "STATE":1,
    "EDITORDER":4,
    "LOCKED":"",
    "DISPID":0,
    "R3RELEASE":"",
    "AUTHOR":"",
    "CREATEDON":"2024-03-15",
    "CHANGEDBY":"",
    "CHANGEDON":"0000-00-00",
    "MTDDECLTYP":0,
    "MTDABSTRCT":"",
    "MTDFINAL":"",
    "DSRNOTEOM":"",
    "EDTX":"",
    "MTDNEWEXC":"",
    "MTDREPLACE":"",
    "MTDOPTNL":"",
    "MTDAMDPRDONLY":"",
    "MTDAMDPCDSCLNT":"",
    "MTDAMDPCLNTINDEP":"",
    "ATTDECLTYP":0,
    "ATTDYNAMIC":"",
    "ATTGETMTD":"",
    "ATTSETMTD":"",
    "ATTRDONLY":"",
    "ATTVALUE":"",
    "ATTPERSIST":"",
    "ATTBUSOBJ":"",
    "ATTKEYFLD":"",
    "ATTEXPVIRT":0,
    "EVTDECLTYP":0,
    "TYPDUMMY":"",
    "TYPTYPE":1,
    "TYPE":"ZINF_E_RATE_TYPE",
    "TABLEOF":"",
    "SRCROW1":0,
    "SRCCOLUMN1":0,
    "SRCROW2":0,
    "SRCCOLUMN2":0,
    "REFCLSNAME":"",
    "REFINTNAME":"",
    "REFCMPNAME":"",
    "BCMTDINST":"",
    "BCMTDCAT":0,
    "BCMTDDIA":"",
    "BCMTDCOM":"",
    "BCMTDSYN":0,
    "BCEVTCAT":0,
    "TYPESRC_LENG":0,
    "TYPESRC":""
   },
   {
    "CLSNAME":"ZCL_CUSTOM_STK_CORRECTION",
    "CMPNAME":"MV_STOCK_HKONT",
    "VERSION":1,
    "ALIAS":"",
    "REDEFIN":"",
    "EXPOSURE":2,
    "STATE":1,
    "EDITORDER":6,
    "LOCKED":"",
    "DISPID":0,
    "R3RELEASE":"",
    "AUTHOR":"",
    "CREATEDON":"2024-03-15",
    "CHANGEDBY":"",
    "CHANGEDON":"0000-00-00",
    "MTDDECLTYP":0,
    "MTDABSTRCT":"",
    "MTDFINAL":"",
    "DSRNOTEOM":"",
    "EDTX":"",
    "MTDNEWEXC":"",
    "MTDREPLACE":"",
    "MTDOPTNL":"",
    "MTDAMDPRDONLY":"",
    "MTDAMDPCDSCLNT":"",
    "MTDAMDPCLNTINDEP":"",
    "ATTDECLTYP":0,
    "ATTDYNAMIC":"",
    "ATTGETMTD":"",
    "ATTSETMTD":"",
    "ATTRDONLY":"",
    "ATTVALUE":"",
    "ATTPERSIST":"",
    "ATTBUSOBJ":"",
    "ATTKEYFLD":"",
    "ATTEXPVIRT":0,
    "EVTDECLTYP":0,
    "TYPDUMMY":"",
    "TYPTYPE":1,
    "TYPE":"ZINF_E_SAKNR",
    "TABLEOF":"",
    "SRCROW1":0,
    "SRCCOLUMN1":0,
    "SRCROW2":0,
    "SRCCOLUMN2":0,
    "REFCLSNAME":"",
    "REFINTNAME":"",
    "REFCMPNAME":"",
    "BCMTDINST":"",
    "BCMTDCAT":0,
    "BCMTDDIA":"",
    "BCMTDCOM":"",
    "BCMTDSYN":0,
    "BCEVTCAT":0,
    "TYPESRC_LENG":0,
    "TYPESRC":""
   },
   {
    "CLSNAME":"ZCL_CUSTOM_STK_CORRECTION",
    "CMPNAME":"PROCESS_DATA",
    "VERSION":1,
    "ALIAS":"",
    "REDEFIN":"",
    "EXPOSURE":2,
    "STATE":1,
    "EDITORDER":3,
    "LOCKED":"",
    "DISPID":0,
    "R3RELEASE":"",
    "AUTHOR":"",
    "CREATEDON":"2024-03-15",
    "CHANGEDBY":"",
    "CHANGEDON":"0000-00-00",
    "MTDDECLTYP":0,
    "MTDABSTRCT":"",
    "MTDFINAL":"",
    "DSRNOTEOM":"",
    "EDTX":"",
    "MTDNEWEXC":"",
    "MTDREPLACE":"",
    "MTDOPTNL":"",
    "MTDAMDPRDONLY":"",
    "MTDAMDPCDSCLNT":"",
    "MTDAMDPCLNTINDEP":"",
    "ATTDECLTYP":0,
    "ATTDYNAMIC":"",
    "ATTGETMTD":"",
    "ATTSETMTD":"",
    "ATTRDONLY":"",
    "ATTVALUE":"",
    "ATTPERSIST":"",
    "ATTBUSOBJ":"",
    "ATTKEYFLD":"",
    "ATTEXPVIRT":0,
    "EVTDECLTYP":0,
    "TYPDUMMY":"",
    "TYPTYPE":0,
    "TYPE":"",
    "TABLEOF":"",
    "SRCROW1":0,
    "SRCCOLUMN1":0,
    "SRCROW2":0,
    "SRCCOLUMN2":0,
    "REFCLSNAME":"",
    "REFINTNAME":"",
    "REFCMPNAME":"",
    "BCMTDINST":"",
    "BCMTDCAT":0,
    "BCMTDDIA":"",
    "BCMTDCOM":"",
    "BCMTDSYN":0,
    "BCEVTCAT":0,
    "TYPESRC_LENG":0,
    "TYPESRC":""
   },
   {
    "CLSNAME":"ZCL_CUSTOM_STK_CORRECTION",
    "CMPNAME":"SET_DATA",
    "VERSION":1,
    "ALIAS":"",
    "REDEFIN":"",
    "EXPOSURE":2,
    "STATE":1,
    "EDITORDER":4,
    "LOCKED":"",
    "DISPID":0,
    "R3RELEASE":"",
    "AUTHOR":"",
    "CREATEDON":"2024-05-17",
    "CHANGEDBY":"",
    "CHANGEDON":"0000-00-00",
    "MTDDECLTYP":0,
    "MTDABSTRCT":"",
    "MTDFINAL":"",
    "DSRNOTEOM":"",
    "EDTX":"",
    "MTDNEWEXC":"X",
    "MTDREPLACE":"",
    "MTDOPTNL":"",
    "MTDAMDPRDONLY":"",
    "MTDAMDPCDSCLNT":"",
    "MTDAMDPCLNTINDEP":"",
    "ATTDECLTYP":0,
    "ATTDYNAMIC":"",
    "ATTGETMTD":"",
    "ATTSETMTD":"",
    "ATTRDONLY":"",
    "ATTVALUE":"",
    "ATTPERSIST":"",
    "ATTBUSOBJ":"",
    "ATTKEYFLD":"",
    "ATTEXPVIRT":0,
    "EVTDECLTYP":0,
    "TYPDUMMY":"",
    "TYPTYPE":0,
    "TYPE":"",
    "TABLEOF":"",
    "SRCROW1":0,
    "SRCCOLUMN1":0,
    "SRCROW2":0,
    "SRCCOLUMN2":0,
    "REFCLSNAME":"",
    "REFINTNAME":"",
    "REFCMPNAME":"",
    "BCMTDINST":"",
    "BCMTDCAT":0,
    "BCMTDDIA":"",
    "BCMTDCOM":"",
    "BCMTDSYN":0,
    "BCEVTCAT":0,
    "TYPESRC_LENG":0,
    "TYPESRC":""
   }
  ]
 },
 {
  "table":"SEOCOMPOTX",
  "data":
  [
   {
    "CLSNAME":"ZCL_CUSTOM_STK_CORRECTION",
    "CMPNAME":"GET_DATA",
    "LANGU":"E",
    "DESCRIPT":""
   },
   {
    "CLSNAME":"ZCL_CUSTOM_STK_CORRECTION",
    "CMPNAME":"GET_FILTER_PARAMETER",
    "LANGU":"E",
    "DESCRIPT":""
   },
   {
    "CLSNAME":"ZCL_CUSTOM_STK_CORRECTION",
    "CMPNAME":"GV_DATE1",
    "LANGU":"E",
    "DESCRIPT":""
   },
   {
    "CLSNAME":"ZCL_CUSTOM_STK_CORRECTION",
    "CMPNAME":"MO_REGULATIVE_COMMON",
    "LANGU":"E",
    "DESCRIPT":""
   },
   {
    "CLSNAME":"ZCL_CUSTOM_STK_CORRECTION",
    "CMPNAME":"MR_STOCK_HKONT",
    "LANGU":"E",
    "DESCRIPT":""
   },
   {
    "CLSNAME":"ZCL_CUSTOM_STK_CORRECTION",
    "CMPNAME":"MS_BANK_BORT",
    "LANGU":"E",
    "DESCRIPT":""
   },
   {
    "CLSNAME":"ZCL_CUSTOM_STK_CORRECTION",
    "CMPNAME":"MS_BANK_REPORT",
    "LANGU":"E",
    "DESCRIPT":""
   },
   {
    "CLSNAME":"ZCL_CUSTOM_STK_CORRECTION",
    "CMPNAME":"MS_BANK_TRANS",
    "LANGU":"E",
    "DESCRIPT":""
   },
   {
    "CLSNAME":"ZCL_CUSTOM_STK_CORRECTION",
    "CMPNAME":"MS_HKONT",
    "LANGU":"E",
    "DESCRIPT":""
   },
   {
    "CLSNAME":"ZCL_CUSTOM_STK_CORRECTION",
    "CMPNAME":"MS_LOG",
    "LANGU":"E",
    "DESCRIPT":""
   },
   {
    "CLSNAME":"ZCL_CUSTOM_STK_CORRECTION",
    "CMPNAME":"MT_ACCOUNT_BALANCES",
    "LANGU":"E",
    "DESCRIPT":""
   },
   {
    "CLSNAME":"ZCL_CUSTOM_STK_CORRECTION",
    "CMPNAME":"MT_ACC_VAL",
    "LANGU":"E",
    "DESCRIPT":""
   },
   {
    "CLSNAME":"ZCL_CUSTOM_STK_CORRECTION",
    "CMPNAME":"MT_CORR_LOG",
    "LANGU":"E",
    "DESCRIPT":""
   },
   {
    "CLSNAME":"ZCL_CUSTOM_STK_CORRECTION",
    "CMPNAME":"MT_HKONT",
    "LANGU":"E",
    "DESCRIPT":""
   },
   {
    "CLSNAME":"ZCL_CUSTOM_STK_CORRECTION",
    "CMPNAME":"MT_LOG",
    "LANGU":"E",
    "DESCRIPT":""
   },
   {
    "CLSNAME":"ZCL_CUSTOM_STK_CORRECTION",
    "CMPNAME":"MT_SKAT",
    "LANGU":"E",
    "DESCRIPT":""
   },
   {
    "CLSNAME":"ZCL_CUSTOM_STK_CORRECTION",
    "CMPNAME":"MT_STOCK",
    "LANGU":"E",
    "DESCRIPT":""
   },
   {
    "CLSNAME":"ZCL_CUSTOM_STK_CORRECTION",
    "CMPNAME":"MT_STSPE",
    "LANGU":"E",
    "DESCRIPT":""
   },
   {
    "CLSNAME":"ZCL_CUSTOM_STK_CORRECTION",
    "CMPNAME":"MT_T001",
    "LANGU":"E",
    "DESCRIPT":""
   },
   {
    "CLSNAME":"ZCL_CUSTOM_STK_CORRECTION",
    "CMPNAME":"MV_AVARAGE_METHOD",
    "LANGU":"E",
    "DESCRIPT":""
   },
   {
    "CLSNAME":"ZCL_CUSTOM_STK_CORRECTION",
    "CMPNAME":"MV_COMPANY_CODE",
    "LANGU":"E",
    "DESCRIPT":""
   },
   {
    "CLSNAME":"ZCL_CUSTOM_STK_CORRECTION",
    "CMPNAME":"MV_PERIOD",
    "LANGU":"E",
    "DESCRIPT":""
   },
   {
    "CLSNAME":"ZCL_CUSTOM_STK_CORRECTION",
    "CMPNAME":"MV_RLDNR",
    "LANGU":"E",
    "DESCRIPT":""
   },
   {
    "CLSNAME":"ZCL_CUSTOM_STK_CORRECTION",
    "CMPNAME":"MV_RTYPE",
    "LANGU":"E",
    "DESCRIPT":""
   },
   {
    "CLSNAME":"ZCL_CUSTOM_STK_CORRECTION",
    "CMPNAME":"MV_STOCK_HKONT",
    "LANGU":"E",
    "DESCRIPT":""
   },
   {
    "CLSNAME":"ZCL_CUSTOM_STK_CORRECTION",
    "CMPNAME":"PROCESS_DATA",
    "LANGU":"E",
    "DESCRIPT":""
   },
   {
    "CLSNAME":"ZCL_CUSTOM_STK_CORRECTION",
    "CMPNAME":"SET_DATA",
    "LANGU":"E",
    "DESCRIPT":""
   }
  ]
 },
 {
  "table":"SEOIMPLREL",
  "data":
  [
   {
    "CLSNAME":"ZCL_CUSTOM_STK_CORRECTION",
    "CMPNAME":"MO_REGULATIVE_COMMON",
    "VERSION":1,
    "REFCLSNAME":"ZINF_REGULATIVE_COMMON",
    "IRLTYPE":0
   }
  ]
 },
 {
  "table":"SEOMETAREL",
  "data":
  [
   {
    "CLSNAME":"ZCL_CUSTOM_STK_CORRECTION",
    "REFCLSNAME":"IF_OO_ADT_CLASSRUN",
    "VERSION":1,
    "STATE":1,
    "AUTHOR":"",
    "CREATEDON":"2024-03-14",
    "CHANGEDBY":"",
    "CHANGEDON":"0000-00-00",
    "RELTYPE":1,
    "RELNAME":"",
    "EXPOSURE":2,
    "IMPFINAL":"",
    "IMPABSTRCT":"",
    "EDITORDER":1,
    "PARTIALLYIMP":""
   },
   {
    "CLSNAME":"ZCL_CUSTOM_STK_CORRECTION",
    "REFCLSNAME":"IF_RAP_QUERY_PROVIDER",
    "VERSION":1,
    "STATE":1,
    "AUTHOR":"",
    "CREATEDON":"2024-03-14",
    "CHANGEDBY":"",
    "CHANGEDON":"0000-00-00",
    "RELTYPE":1,
    "RELNAME":"",
    "EXPOSURE":2,
    "IMPFINAL":"",
    "IMPABSTRCT":"",
    "EDITORDER":2,
    "PARTIALLYIMP":""
   }
  ]
 },
 {
  "table":"SEOSUBCO",
  "data":
  [
   {
    "CLSNAME":"ZCL_CUSTOM_STK_CORRECTION",
    "CMPNAME":"GET_FILTER_PARAMETER",
    "SCONAME":"IO_REQUEST",
    "CMPTYPE":1,
    "MTDTYPE":0,
    "SCOTYPE":0
   },
   {
    "CLSNAME":"ZCL_CUSTOM_STK_CORRECTION",
    "CMPNAME":"SET_DATA",
    "SCONAME":"CX_RAP_QUERY_PROVIDER",
    "CMPTYPE":1,
    "MTDTYPE":0,
    "SCOTYPE":1
   },
   {
    "CLSNAME":"ZCL_CUSTOM_STK_CORRECTION",
    "CMPNAME":"SET_DATA",
    "SCONAME":"CX_RAP_QUERY_PROV_NOT_IMPL",
    "CMPTYPE":1,
    "MTDTYPE":0,
    "SCOTYPE":1
   },
   {
    "CLSNAME":"ZCL_CUSTOM_STK_CORRECTION",
    "CMPNAME":"SET_DATA",
    "SCONAME":"IO_REQUEST",
    "CMPTYPE":1,
    "MTDTYPE":0,
    "SCOTYPE":0
   },
   {
    "CLSNAME":"ZCL_CUSTOM_STK_CORRECTION",
    "CMPNAME":"SET_DATA",
    "SCONAME":"IO_RESPONSE",
    "CMPTYPE":1,
    "MTDTYPE":0,
    "SCOTYPE":0
   }
  ]
 },
 {
  "table":"SEOSUBCODF",
  "data":
  [
   {
    "CLSNAME":"ZCL_CUSTOM_STK_CORRECTION",
    "CMPNAME":"GET_FILTER_PARAMETER",
    "SCONAME":"IO_REQUEST",
    "VERSION":1,
    "EDITORDER":1,
    "LOCKED":"",
    "DISPID":0,
    "AUTHOR":"SAP_CUSTOMER",
    "CREATEDON":"2024-03-15",
    "CHANGEDBY":"",
    "CHANGEDON":"0000-00-00",
    "PARDECLTYP":0,
    "PARPASSTYP":0,
    "TYPTYPE":3,
    "TYPE":"IF_RAP_QUERY_REQUEST",
    "TABLEOF":"",
    "SRCROW1":0,
    "SRCCOLUMN1":0,
    "SRCROW2":0,
    "SRCCOLUMN2":0,
    "PARVALUE":"",
    "PAROPTIONL":"",
    "PARPREFERD":"",
    "EXCDECLTYP":0,
    "IS_RESUMABLE":""
   },
   {
    "CLSNAME":"ZCL_CUSTOM_STK_CORRECTION",
    "CMPNAME":"SET_DATA",
    "SCONAME":"CX_RAP_QUERY_PROVIDER",
    "VERSION":1,
    "EDITORDER":2,
    "LOCKED":"",
    "DISPID":0,
    "AUTHOR":"SAP_CUSTOMER",
    "CREATEDON":"2024-05-17",
    "CHANGEDBY":"",
    "CHANGEDON":"0000-00-00",
    "PARDECLTYP":0,
    "PARPASSTYP":0,
    "TYPTYPE":0,
    "TYPE":"",
    "TABLEOF":"",
    "SRCROW1":0,
    "SRCCOLUMN1":0,
    "SRCROW2":0,
    "SRCCOLUMN2":0,
    "PARVALUE":"",
    "PAROPTIONL":"",
    "PARPREFERD":"",
    "EXCDECLTYP":0,
    "IS_RESUMABLE":""
   },
   {
    "CLSNAME":"ZCL_CUSTOM_STK_CORRECTION",
    "CMPNAME":"SET_DATA",
    "SCONAME":"CX_RAP_QUERY_PROV_NOT_IMPL",
    "VERSION":1,
    "EDITORDER":1,
    "LOCKED":"",
    "DISPID":0,
    "AUTHOR":"SAP_CUSTOMER",
    "CREATEDON":"2024-05-17",
    "CHANGEDBY":"",
    "CHANGEDON":"0000-00-00",
    "PARDECLTYP":0,
    "PARPASSTYP":0,
    "TYPTYPE":0,
    "TYPE":"",
    "TABLEOF":"",
    "SRCROW1":0,
    "SRCCOLUMN1":0,
    "SRCROW2":0,
    "SRCCOLUMN2":0,
    "PARVALUE":"",
    "PAROPTIONL":"",
    "PARPREFERD":"",
    "EXCDECLTYP":0,
    "IS_RESUMABLE":""
   },
   {
    "CLSNAME":"ZCL_CUSTOM_STK_CORRECTION",
    "CMPNAME":"SET_DATA",
    "SCONAME":"IO_REQUEST",
    "VERSION":1,
    "EDITORDER":1,
    "LOCKED":"",
    "DISPID":0,
    "AUTHOR":"SAP_CUSTOMER",
    "CREATEDON":"2024-05-17",
    "CHANGEDBY":"",
    "CHANGEDON":"0000-00-00",
    "PARDECLTYP":0,
    "PARPASSTYP":1,
    "TYPTYPE":3,
    "TYPE":"IF_RAP_QUERY_REQUEST",
    "TABLEOF":"",
    "SRCROW1":0,
    "SRCCOLUMN1":0,
    "SRCROW2":0,
    "SRCCOLUMN2":0,
    "PARVALUE":"",
    "PAROPTIONL":"X",
    "PARPREFERD":"",
    "EXCDECLTYP":0,
    "IS_RESUMABLE":""
   },
   {
    "CLSNAME":"ZCL_CUSTOM_STK_CORRECTION",
    "CMPNAME":"SET_DATA",
    "SCONAME":"IO_RESPONSE",
    "VERSION":1,
    "EDITORDER":2,
    "LOCKED":"",
    "DISPID":0,
    "AUTHOR":"SAP_CUSTOMER",
    "CREATEDON":"2024-05-17",
    "CHANGEDBY":"",
    "CHANGEDON":"0000-00-00",
    "PARDECLTYP":0,
    "PARPASSTYP":1,
    "TYPTYPE":3,
    "TYPE":"IF_RAP_QUERY_RESPONSE",
    "TABLEOF":"",
    "SRCROW1":0,
    "SRCCOLUMN1":0,
    "SRCROW2":0,
    "SRCCOLUMN2":0,
    "PARVALUE":"",
    "PAROPTIONL":"X",
    "PARPREFERD":"",
    "EXCDECLTYP":0,
    "IS_RESUMABLE":""
   }
  ]
 },
 {
  "table":"SEOSUBCOTX",
  "data":
  [
   {
    "CLSNAME":"ZCL_CUSTOM_STK_CORRECTION",
    "CMPNAME":"GET_FILTER_PARAMETER",
    "SCONAME":"IO_REQUEST",
    "LANGU":"E",
    "DESCRIPT":""
   },
   {
    "CLSNAME":"ZCL_CUSTOM_STK_CORRECTION",
    "CMPNAME":"SET_DATA",
    "SCONAME":"CX_RAP_QUERY_PROVIDER",
    "LANGU":"E",
    "DESCRIPT":""
   },
   {
    "CLSNAME":"ZCL_CUSTOM_STK_CORRECTION",
    "CMPNAME":"SET_DATA",
    "SCONAME":"CX_RAP_QUERY_PROV_NOT_IMPL",
    "LANGU":"E",
    "DESCRIPT":""
   },
   {
    "CLSNAME":"ZCL_CUSTOM_STK_CORRECTION",
    "CMPNAME":"SET_DATA",
    "SCONAME":"IO_REQUEST",
    "LANGU":"E",
    "DESCRIPT":""
   },
   {
    "CLSNAME":"ZCL_CUSTOM_STK_CORRECTION",
    "CMPNAME":"SET_DATA",
    "SCONAME":"IO_RESPONSE",
    "LANGU":"E",
    "DESCRIPT":""
   }
  ]
 },
 {
  "table":"TADIR",
  "data":
  [
   {
    "PGMID":"R3TR",
    "OBJECT":"CLAS",
    "OBJ_NAME":"ZCL_CUSTOM_STK_CORRECTION",
    "KORRNUM":"",
    "SRCSYSTEM":"...",
    "AUTHOR":"SAP_CUSTOMER",
    "SRCDEP":"",
    "DEVCLASS":"ZINFLATION0",
    "GENFLAG":"",
    "EDTFLAG":"",
    "CPROJECT":" L",
    "MASTERLANG":"E",
    "VERSID":"",
    "PAKNOCHECK":"",
    "OBJSTABLTY":"",
    "COMPONENT":"",
    "CRELEASE":"",
    "DELFLAG":"",
    "TRANSLTTXT":"",
    "CREATED_ON":"2024-03-14",
    "CHECK_DATE":"2024-03-14",
    "CHECK_CFG":""
   }
  ]
 },
 {
  "table":"TMDIR",
  "data":
  [
   {
    "CLASSNAME":"ZCL_CUSTOM_STK_CORRECTION",
    "METHODINDX":0,
    "METHODNAME":" ",
    "FLAGS":0
   },
   {
    "CLASSNAME":"ZCL_CUSTOM_STK_CORRECTION",
    "METHODINDX":1,
    "METHODNAME":"IF_OO_ADT_CLASSRUN~MAIN",
    "FLAGS":0
   },
   {
    "CLASSNAME":"ZCL_CUSTOM_STK_CORRECTION",
    "METHODINDX":2,
    "METHODNAME":"IF_RAP_QUERY_PROVIDER~SELECT",
    "FLAGS":0
   },
   {
    "CLASSNAME":"ZCL_CUSTOM_STK_CORRECTION",
    "METHODINDX":3,
    "METHODNAME":"GET_FILTER_PARAMETER",
    "FLAGS":0
   },
   {
    "CLASSNAME":"ZCL_CUSTOM_STK_CORRECTION",
    "METHODINDX":4,
    "METHODNAME":"GET_DATA",
    "FLAGS":0
   },
   {
    "CLASSNAME":"ZCL_CUSTOM_STK_CORRECTION",
    "METHODINDX":5,
    "METHODNAME":"PROCESS_DATA",
    "FLAGS":0
   },
   {
    "CLASSNAME":"ZCL_CUSTOM_STK_CORRECTION",
    "METHODINDX":6,
    "METHODNAME":"SET_DATA",
    "FLAGS":0
   }
  ]
 },
 {
  "table":"TRDIR",
  "data":
  [
   {
    "NAME":"ZCL_CUSTOM_STK_CORRECTION=====CCAU",
    "VARCL":"X",
    "DBAPL":"S",
    "DBNA":"D$",
    "SUBC":"I",
    "APPL":"S",
    "FIXPT":"X",
    "LDBNAME":"D$S",
    "UCCHECK":"X"
   },
   {
    "NAME":"ZCL_CUSTOM_STK_CORRECTION=====CCDEF",
    "VARCL":"X",
    "DBAPL":"S",
    "DBNA":"D$",
    "SUBC":"I",
    "APPL":"S",
    "FIXPT":"X",
    "LDBNAME":"D$S",
    "UCCHECK":"X"
   },
   {
    "NAME":"ZCL_CUSTOM_STK_CORRECTION=====CCIMP",
    "VARCL":"X",
    "DBAPL":"S",
    "DBNA":"D$",
    "SUBC":"I",
    "APPL":"S",
    "FIXPT":"X",
    "LDBNAME":"D$S",
    "UCCHECK":"X"
   },
   {
    "NAME":"ZCL_CUSTOM_STK_CORRECTION=====CCMAC",
    "VARCL":"X",
    "DBAPL":"S",
    "DBNA":"D$",
    "SUBC":"I",
    "APPL":"S",
    "FIXPT":"X",
    "LDBNAME":"D$S",
    "UCCHECK":"X"
   },
   {
    "NAME":"ZCL_CUSTOM_STK_CORRECTION=====CI",
    "VARCL":"X",
    "DBAPL":"S",
    "DBNA":"D$",
    "SUBC":"I",
    "APPL":"S",
    "FIXPT":"X",
    "LDBNAME":"D$S",
    "UCCHECK":"X"
   },
   {
    "NAME":"ZCL_CUSTOM_STK_CORRECTION=====CM001",
    "VARCL":"X",
    "DBAPL":"S",
    "DBNA":"D$",
    "SUBC":"I",
    "APPL":"S",
    "FIXPT":"X",
    "LDBNAME":"D$S",
    "UCCHECK":"X"
   },
   {
    "NAME":"ZCL_CUSTOM_STK_CORRECTION=====CM002",
    "VARCL":"X",
    "DBAPL":"S",
    "DBNA":"D$",
    "SUBC":"I",
    "APPL":"S",
    "FIXPT":"X",
    "LDBNAME":"D$S",
    "UCCHECK":"X"
   },
   {
    "NAME":"ZCL_CUSTOM_STK_CORRECTION=====CM003",
    "VARCL":"X",
    "DBAPL":"S",
    "DBNA":"D$",
    "SUBC":"I",
    "APPL":"S",
    "FIXPT":"X",
    "LDBNAME":"D$S",
    "UCCHECK":"X"
   },
   {
    "NAME":"ZCL_CUSTOM_STK_CORRECTION=====CM004",
    "VARCL":"X",
    "DBAPL":"S",
    "DBNA":"D$",
    "SUBC":"I",
    "APPL":"S",
    "FIXPT":"X",
    "LDBNAME":"D$S",
    "UCCHECK":"X"
   },
   {
    "NAME":"ZCL_CUSTOM_STK_CORRECTION=====CM005",
    "VARCL":"X",
    "DBAPL":"S",
    "DBNA":"D$",
    "SUBC":"I",
    "APPL":"S",
    "FIXPT":"X",
    "LDBNAME":"D$S",
    "UCCHECK":"X"
   },
   {
    "NAME":"ZCL_CUSTOM_STK_CORRECTION=====CM006",
    "VARCL":"X",
    "DBAPL":"S",
    "DBNA":"D$",
    "SUBC":"I",
    "APPL":"S",
    "FIXPT":"X",
    "LDBNAME":"D$S",
    "UCCHECK":"X"
   },
   {
    "NAME":"ZCL_CUSTOM_STK_CORRECTION=====CO",
    "VARCL":"X",
    "DBAPL":"S",
    "DBNA":"D$",
    "SUBC":"I",
    "APPL":"S",
    "FIXPT":"X",
    "LDBNAME":"D$S",
    "UCCHECK":"X"
   },
   {
    "NAME":"ZCL_CUSTOM_STK_CORRECTION=====CP",
    "EDTX":"X",
    "VARCL":"X",
    "DBAPL":"S",
    "DBNA":"D$",
    "SUBC":"K",
    "APPL":"S",
    "FIXPT":"X",
    "LDBNAME":"D$S",
    "UCCHECK":"5"
   },
   {
    "NAME":"ZCL_CUSTOM_STK_CORRECTION=====CT",
    "DBAPL":"S",
    "DBNA":"D$",
    "SUBC":"I",
    "APPL":"S",
    "FIXPT":"X",
    "LDBNAME":"D$S",
    "UCCHECK":"X"
   },
   {
    "NAME":"ZCL_CUSTOM_STK_CORRECTION=====CU",
    "VARCL":"X",
    "DBAPL":"S",
    "DBNA":"D$",
    "SUBC":"I",
    "APPL":"S",
    "FIXPT":"X",
    "LDBNAME":"D$S",
    "UCCHECK":"X"
   }
  ]
 }
]