[
 {
  "table":"DD04L",
  "data":
  [
   {
    "ROLLNAME":"ZINF_E_SERVICE_URL",
    "AS4LOCAL":"L",
    "AS4VERS":0,
    "DOMNAME":"",
    "ROUTPUTLEN":0,
    "MEMORYID":"",
    "LOGFLAG":"",
    "HEADLEN":55,
    "SCRLEN1":10,
    "SCRLEN2":20,
    "SCRLEN3":40,
    "ACTFLAG":"",
    "APPLCLASS":"",
    "AUTHCLASS":0,
    "AS4USER":"SAP_CUSTOMER",
    "AS4DATE":"0000-00-00",
    "AS4TIME":"00:00:00",
    "DTELMASTER":"E",
    "RESERVEDTE":"",
    "DTELGLOBAL":"",
    "SHLPNAME":"",
    "SHLPFIELD":"",
    "DEFFDNAME":"",
    "DATATYPE":"CHAR",
    "LENG":255,
    "DECIMALS":0,
    "OUTPUTLEN":255,
    "LOWERCASE":"",
    "SIGNFLAG":"",
    "CONVEXIT":"",
    "VALEXI":"",
    "ENTITYTAB":"",
    "REFKIND":"",
    "REFTYPE":"",
    "PROXYTYPE":"",
    "LTRFLDDIS":"",
    "BIDICTRLC":"",
    "NOHISTORY":"",
    "ABAP_LANGUAGE_VERSION":"5"
   }
  ]
 },
 {
  "table":"DD04T",
  "data":
  [
   {
    "ROLLNAME":"ZINF_E_SERVICE_URL",
    "DDLANGUAGE":"E",
    "AS4LOCAL":"N",
    "AS4VERS":0,
    "DDTEXT":"Service URL",
    "REPTEXT":"Servis URL",
    "SCRTEXT_S":"Servis URL",
    "SCRTEXT_M":"Servis URL",
    "SCRTEXT_L":"Servis URL"
   }
  ]
 },
 {
  "table":"DDTYPES",
  "data":
  [
   {
    "TYPENAME":"ZINF_E_SERVICE_URL",
    "STATE":"N",
    "TYPEKIND":"DTEL"
   }
  ]
 },
 {
  "table":"TADIR",
  "data":
  [
   {
    "PGMID":"R3TR",
    "OBJECT":"DTEL",
    "OBJ_NAME":"ZINF_E_SERVICE_URL",
    "KORRNUM":"",
    "SRCSYSTEM":"...",
    "AUTHOR":"SAP_CUSTOMER",
    "SRCDEP":"",
    "DEVCLASS":"ZINFLATION0",
    "GENFLAG":"",
    "EDTFLAG":"",
    "CPROJECT":" L",
    "MASTERLANG":"E",
    "VERSID":"",
    "PAKNOCHECK":"",
    "OBJSTABLTY":"",
    "COMPONENT":"",
    "CRELEASE":"",
    "DELFLAG":"",
    "TRANSLTTXT":"",
    "CREATED_ON":"2024-01-23",
    "CHECK_DATE":"2024-01-23",
    "CHECK_CFG":""
   }
  ]
 }
]