[
 {
  "table":"SRVDSRC",
  "data":
  [
   {
    "SRVDNAME":"ZD_CUSTOM_STOCK_TRANS_SPEED",
    "VERSION":"A",
    "CHANGED_BY":"SAP_CUSTOMER",
    "CHANGED_ON":"2023-11-09",
    "CHANGED_AT":"11:45:47",
    "DT_UUID":"B70B55EC7ED81EDE9FDEB0A60860DE8F",
    "SOURCE_ORIGIN":"0",
    "SRVD_SOURCE_TYPE":"S",
    "ABAP_LANGUAGE_VERSION":"5"
   }
  ]
 },
 {
  "table":"SRVDSRCT",
  "data":
  [
   {
    "SRVDNAME":"ZD_CUSTOM_STOCK_TRANS_SPEED",
    "VERSION":"A",
    "LANGUAGE":"E",
    "DESCRIPTION":"Service Definition for Stok Devir Hızı"
   }
  ]
 },
 {
  "table":"SRVDSRC_SRC",
  "data":
  [
   {
    "SRVDNAME":"ZD_CUSTOM_STOCK_TRANS_SPEED",
    "VERSION":"A",
    "SOURCE":"@EndUserText.label: 'Service Definition for Stok Devir Hızı'\r\ndefine service ZD_CUSTOM_STOCK_TRANS_SPEED {\r\n  expose ZINF_CUSTOM_STOCK_TRANS_SPEED as stokDevirHizi;\r\n}"
   }
  ]
 },
 {
  "table":"SRVD_RT_ANNOS",
  "data":
  [
   {
    "SRVDNAME":"ZD_CUSTOM_STOCK_TRANS_SPEED",
    "NAME":"ENDUSERTEXT.LABEL",
    "VALUE":"'Service Definition for Stok Devir Hızı'"
   }
  ]
 },
 {
  "table":"SRVD_RT_ANNOS_T",
  "data":
  [
   {
    "SRVDNAME":"ZD_CUSTOM_STOCK_TRANS_SPEED",
    "LANGUAGE":"E",
    "NAME":"ENDUSERTEXT.LABEL",
    "TEXT":"Service Definition for Stok Devir Hızı"
   }
  ]
 },
 {
  "table":"SRVD_RT_ENTITIES",
  "data":
  [
   {
    "SRVDNAME":"ZD_CUSTOM_STOCK_TRANS_SPEED",
    "SERVICE":"ZD_CUSTOM_STOCK_TRANS_SPEED",
    "EXPOSED_ARTIFACT":"ZINF_CUSTOM_STOCK_TRANS_SPEED",
    "EXPOSED_ARTIFACT_TYPE":"E",
    "EXPOSED_ALIAS":"STOKDEVIRHIZI",
    "EXPOSED_ALIAS_RAW":"stokDevirHizi",
    "INCL_SERVICE":""
   }
  ]
 },
 {
  "table":"SRVD_RT_HEADER",
  "data":
  [
   {
    "SRVDNAME":"ZD_CUSTOM_STOCK_TRANS_SPEED",
    "SERVICE":"ZD_CUSTOM_STOCK_TRANS_SPEED",
    "SERVICE_RAW":"ZD_CUSTOM_STOCK_TRANS_SPEED",
    "SOURCE_TYPE":"S",
    "DT_UUID":"B70B55EC7ED81EDE9FDEB0A60860DE8F",
    "RT_HASH":"66C698728DA06C0FE94AF7D9D5CDE0C78B364B49",
    "GEN_VERSION":"0"
   }
  ]
 },
 {
  "table":"TADIR",
  "data":
  [
   {
    "PGMID":"R3TR",
    "OBJECT":"SRVD",
    "OBJ_NAME":"ZD_CUSTOM_STOCK_TRANS_SPEED",
    "KORRNUM":"",
    "SRCSYSTEM":"...",
    "AUTHOR":"SAP_CUSTOMER",
    "SRCDEP":"",
    "DEVCLASS":"ZINFLATION0",
    "GENFLAG":"",
    "EDTFLAG":"",
    "CPROJECT":" L",
    "MASTERLANG":"E",
    "VERSID":"",
    "PAKNOCHECK":"",
    "OBJSTABLTY":"",
    "COMPONENT":"",
    "CRELEASE":"",
    "DELFLAG":"",
    "TRANSLTTXT":"",
    "CREATED_ON":"2023-11-09",
    "CHECK_DATE":"2023-11-09",
    "CHECK_CFG":""
   }
  ]
 }
]