[
 {
  "table":"/IWFND/I_MED_NOD",
  "nametab":
  [
   {
    "NAME":"MODEL_IDENTIFIER",
    "KEY":"X",
    "TYPE":"C",
    "LENGTH":40,
    "DECIMALS":-1
   },
   {
    "NAME":"IS_ACTIVE",
    "KEY":"X",
    "TYPE":"C",
    "LENGTH":1,
    "DECIMALS":-1
   },
   {
    "NAME":"ENTITY_ID",
    "KEY":"X",
    "TYPE":"C",
    "LENGTH":34,
    "DECIMALS":-1
   },
   {
    "NAME":"SUBSCRIBABLE",
    "KEY":"",
    "TYPE":"C",
    "LENGTH":1,
    "DECIMALS":-1
   },
   {
    "NAME":"CREATABLE",
    "KEY":"",
    "TYPE":"C",
    "LENGTH":1,
    "DECIMALS":-1
   },
   {
    "NAME":"UPDATABLE",
    "KEY":"",
    "TYPE":"C",
    "LENGTH":1,
    "DECIMALS":-1
   },
   {
    "NAME":"DELETABLE",
    "KEY":"",
    "TYPE":"C",
    "LENGTH":1,
    "DECIMALS":-1
   },
   {
    "NAME":"PAGEABLE",
    "KEY":"",
    "TYPE":"C",
    "LENGTH":1,
    "DECIMALS":-1
   },
   {
    "NAME":"ADDRESSABLE",
    "KEY":"",
    "TYPE":"C",
    "LENGTH":1,
    "DECIMALS":-1
   },
   {
    "NAME":"ATTRIBUTE_STRUCT",
    "KEY":"",
    "TYPE":"U",
    "LENGTH":8,
    "DECIMALS":-1
   },
   {
    "NAME":"KEY_STRUCT",
    "KEY":"",
    "TYPE":"U",
    "LENGTH":8,
    "DECIMALS":-1
   },
   {
    "NAME":"TYPE",
    "KEY":"",
    "TYPE":"C",
    "LENGTH":1,
    "DECIMALS":-1
   },
   {
    "NAME":"IS_MEDIA_TYPE",
    "KEY":"",
    "TYPE":"C",
    "LENGTH":1,
    "DECIMALS":-1
   },
   {
    "NAME":"FREETEXT_SEARCH",
    "KEY":"",
    "TYPE":"C",
    "LENGTH":1,
    "DECIMALS":-1
   },
   {
    "NAME":"FILTER_REQUIRED",
    "KEY":"",
    "TYPE":"C",
    "LENGTH":1,
    "DECIMALS":-1
   },
   {
    "NAME":"ABSTRACT",
    "KEY":"",
    "TYPE":"C",
    "LENGTH":1,
    "DECIMALS":-1
   },
   {
    "NAME":"ENTITY_SET_NAME",
    "KEY":"",
    "TYPE":"C",
    "LENGTH":40,
    "DECIMALS":-1
   }
  ],
  "properties":
  [
   {
    "CLIENTDEPENDENCY":"NO",
    "DELIVERYCLASS":"W",
    "TABART":"APPL0",
    "TABFORM":"T",
    "REFNAME":"-"
   }
  ]
 }
]